datagusto_sdk/__init__.py
datagusto_sdk/middleware.py
datagusto_sdk-0.1.7.dist-info/licenses/LICENSE
datagusto_sdk-0.1.7.dist-info/METADATA
datagusto_sdk-0.1.7.dist-info/WHEEL
datagusto_sdk-0.1.7.dist-info/top_level.txt
datagusto_sdk-0.1.7.dist-info/RECORD
