Metadata-Version: 2.4
Name: datagusto-sdk
Version: 0.1.7
Summary: Datagusto safety middleware for LangChain/LangGraph agents
Author-email: Datagusto <support@datagusto.com>
License: MIT
Project-URL: Homepage, https://pypi.org/project/datagusto-sdk/
Project-URL: Bug Tracker, https://pypi.org/project/datagusto-sdk/
Keywords: langchain,langgraph,agent,middleware,safety,guardrails,alignment
Classifier: Development Status :: 3 - Alpha
Classifier: Intended Audience :: Developers
Classifier: License :: OSI Approved :: MIT License
Classifier: Programming Language :: Python
Classifier: Programming Language :: Python :: 3
Classifier: Programming Language :: Python :: 3.12
Classifier: Topic :: Scientific/Engineering :: Artificial Intelligence
Classifier: Topic :: Software Development :: Libraries :: Python Modules
Requires-Python: >=3.12
License-File: LICENSE
Requires-Dist: langchain>=1.2.0
Requires-Dist: langgraph>=1.0.5
Dynamic: license-file
